json2hive/__about__.py
json2hive/__init__.py
json2hive/cli.py
json2hive/generators.py
json2hive/utils.py
json2hive-0.1.dist-info/DESCRIPTION.rst
json2hive-0.1.dist-info/METADATA
json2hive-0.1.dist-info/RECORD
json2hive-0.1.dist-info/WHEEL
json2hive-0.1.dist-info/entry_points.txt
json2hive-0.1.dist-info/metadata.json
json2hive-0.1.dist-info/top_level.txt
