Metadata-Version: 2.0
Name: json2hive
Version: 0.1
Summary: Generate Hive CREATE TABLE statements from json data
Home-page: https://github.com/datadudes/json2hive
Author: Daan Debie
Author-email: daan.debie@klm.com
License: MIT
Keywords: slack bot framework ai
Platform: UNKNOWN
Classifier: Development Status :: 3 - Alpha
Classifier: Intended Audience :: Developers
Classifier: License :: OSI Approved :: MIT License
Classifier: Natural Language :: English
Classifier: Operating System :: OS Independent
Classifier: Programming Language :: Python :: 3.3
Classifier: Programming Language :: Python :: 3.4
Classifier: Programming Language :: Python :: 3.5
Classifier: Programming Language :: Python :: 3.6
Classifier: Programming Language :: Python :: 3 :: Only
Requires-Python: ~=3.3
Requires-Dist: genson (==0.2.3)
